sato_ble_vision/__init__.py
sato_ble_vision/api_handler.py
sato_ble_vision/broker.py
sato_ble_vision/config.py
sato_ble_vision/main.py
sato_ble_vision/mqtt_client.py
sato_ble_vision/settings.py
sato_ble_vision/pics/logo_b.png
sato_ble_vision/pics/logo_w.png
sato_ble_vision/pics/mqtt.png
sato_ble_vision/pics/offline.png
sato_ble_vision/pics/online.png
sato_ble_vision/pics/settings.png
sato_ble_vision/pics/settingsv2.png
sato_ble_vision/pics/settingsv3.png
sato_ble_vision/pics/test.png
sato_ble_vision/templates/configuration_template.json
sato_ble_vision-1.0.1.dist-info/LICENSE
sato_ble_vision-1.0.1.dist-info/METADATA
sato_ble_vision-1.0.1.dist-info/WHEEL
sato_ble_vision-1.0.1.dist-info/entry_points.txt
sato_ble_vision-1.0.1.dist-info/top_level.txt
sato_ble_vision-1.0.1.dist-info/RECORD
