Metadata-Version: 2.1
Name: sato-ble-vision
Version: 1.0.1
Summary: MQTT Broker Control and IoT Data Management Tool
Home-page: https://github.com/dylanbarnett99/sato-ble
Author: Dylan Barnett
Author-email: dylanbarnett99@gmail.com
Project-URL: Bug Reports, https://github.com/dylanbarnett99/sato-ble/issues
Project-URL: Source, https://github.com/dylanbarnett99/sato-ble
Keywords: mqtt,iot,broker,data,management
Classifier: Development Status :: 4 - Beta
Classifier: Intended Audience :: Developers
Classifier: License :: OSI Approved :: MIT License
Classifier: Operating System :: OS Independent
Classifier: Programming Language :: Python :: 3
Classifier: Programming Language :: Python :: 3.7
Classifier: Programming Language :: Python :: 3.8
Classifier: Programming Language :: Python :: 3.9
Classifier: Programming Language :: Python :: 3.10
Classifier: Programming Language :: Python :: 3.11
Classifier: Topic :: Communications
Classifier: Topic :: Internet
Classifier: Topic :: Software Development :: Libraries :: Python Modules
Requires-Python: >=3.7
License-File: LICENSE
Requires-Dist: paho-mqtt >=1.6.0
Requires-Dist: pandas >=1.3.0
Requires-Dist: psutil >=5.8.0
Requires-Dist: requests >=2.25.0
